{
  "project_info": {
    "project_number": "95085555633",
    "firebase_url": "https://rednotes-app-default-rtdb.firebaseio.com",
    "project_id": "rednotes-app",
    "storage_bucket": "rednotes-app.appspot.com"
  },
  "client": [
    {
      "client_info": {
        "mobilesdk_app_id": "1:95085555633:android:88a42ea802039a3a359790",
        "android_client_info": {
          "package_name": "com.example.admin_pannel"
        }
      },
      "oauth_client": [
        {
          "client_id": "95085555633-c8q30rho3rnkg76dr1cqdu5cu0br6sdh.apps.googleusercontent.com",
          "client_type": 3
        }
      ],
      "api_key": [
        {
          "current_key": "AIzaSyCnYo1LubaneTXgVX9ZhUW7BC4A8FrnNt8"
        }
      ],
      "services": {
        "appinvite_service": {
          "other_platform_oauth_client": [
            {
              "client_id": "95085555633-c8q30rho3rnkg76dr1cqdu5cu0br6sdh.apps.googleusercontent.com",
              "client_type": 3
            }
          ]
        }
      }
    },
    {
      "client_info": {
        "mobilesdk_app_id": "1:95085555633:android:8141ff99d2c69c4e359790",
        "android_client_info": {
          "package_name": "com.example.red_note_admin_pannel"
        }
      },
      "oauth_client": [
        {
          "client_id": "95085555633-c8q30rho3rnkg76dr1cqdu5cu0br6sdh.apps.googleusercontent.com",
          "client_type": 3
        }
      ],
      "api_key": [
        {
          "current_key": "AIzaSyCnYo1LubaneTXgVX9ZhUW7BC4A8FrnNt8"
        }
      ],
      "services": {
        "appinvite_service": {
          "other_platform_oauth_client": [
            {
              "client_id": "95085555633-c8q30rho3rnkg76dr1cqdu5cu0br6sdh.apps.googleusercontent.com",
              "client_type": 3
            }
          ]
        }
      }
    },
    {
      "client_info": {
        "mobilesdk_app_id": "1:95085555633:android:d45d4611baebc16f359790",
        "android_client_info": {
          "package_name": "com.sahil.rednote"
        }
      },
      "oauth_client": [
        {
          "client_id": "95085555633-c8q30rho3rnkg76dr1cqdu5cu0br6sdh.apps.googleusercontent.com",
          "client_type": 3
        }
      ],
      "api_key": [
        {
          "current_key": "AIzaSyCnYo1LubaneTXgVX9ZhUW7BC4A8FrnNt8"
        }
      ],
      "services": {
        "appinvite_service": {
          "other_platform_oauth_client": [
            {
              "client_id": "95085555633-c8q30rho3rnkg76dr1cqdu5cu0br6sdh.apps.googleusercontent.com",
              "client_type": 3
            }
          ]
        }
      }
    },
    {
      "client_info": {
        "mobilesdk_app_id": "1:95085555633:android:b8d13d3036f06805359790",
        "android_client_info": {
          "package_name": "com.sahil.rednotesapp"
        }
      },
      "oauth_client": [
        {
          "client_id": "95085555633-c8q30rho3rnkg76dr1cqdu5cu0br6sdh.apps.googleusercontent.com",
          "client_type": 3
        }
      ],
      "api_key": [
        {
          "current_key": "AIzaSyCnYo1LubaneTXgVX9ZhUW7BC4A8FrnNt8"
        }
      ],
      "services": {
        "appinvite_service": {
          "other_platform_oauth_client": [
            {
              "client_id": "95085555633-c8q30rho3rnkg76dr1cqdu5cu0br6sdh.apps.googleusercontent.com",
              "client_type": 3
            }
          ]
        }
      }
    }
  ],
  "configuration_version": "1"
}